{
  "weekly_menu_list": [
    {
      "date": "Segunda-feira - 25/06/2018",
      "main_course": "Linguiça assada",
      "guarnicao": "Quibebe de mandioca com acafrao",
      "salada": "Repolho, cenoura e tomate",
      "acompanhamento": "Arroz branco e feijao carioca",
      "sobremesa": "Doce de leite com amendoin"
    },
    {
      "date": "Terca-feira - 26/06/2018",
      "main_course": "Frango grelhado",
      "guarnicao": "Pure de batata com banana",
      "salada": "Alface, tomate e beterraba",
      "acompanhamento": "Arroz branco e feijao carioca",
      "sobremesa": "Melancia"
    },
    {
      "date": "Quarta-feira - 27/06/2018",
      "main_course": "Carne suína acebolada",
      "guarnicao": "Legumes salteados",
      "salada": "Alface, cenoura e pepino",
      "acompanhamento": "Arroz branco e tutu de feijao",
      "sobremesa": "Banana"
    },
    {
      "date": "Quinta-feira - 28/06/2018",
      "main_course": "Galinha",
      "guarnicao": "Cuscuz",
      "salada": "Acelga com laranja e tomate",
      "acompanhamento": "Feijao carioca",
      "sobremesa": "Canjica ou Pacoca"
    },
    {
      "date": "Sexta-feira - 29/06/2018",
      "main_course": "Fijoada",
      "guarnicao": "Virado de couve",
      "salada": "Alface e vinagrete",
      "acompanhamento": "Arroz branco",
      "sobremesa": "Laranja"
    }
  ]
}
